res_mlp_pytorch/__init__.py
res_mlp_pytorch/res_mlp_pytorch.py
res_mlp_pytorch-0.0.6.dist-info/LICENSE
res_mlp_pytorch-0.0.6.dist-info/METADATA
res_mlp_pytorch-0.0.6.dist-info/WHEEL
res_mlp_pytorch-0.0.6.dist-info/top_level.txt
res_mlp_pytorch-0.0.6.dist-info/RECORD
